audbackend/__init__.py
audbackend/backend/__init__.py
audbackend/core/__init__.py
audbackend/core/conftest.py
audbackend/core/errors.py
audbackend/core/repository.py
audbackend/core/utils.py
audbackend/core/backend/__init__.py
audbackend/core/backend/artifactory.py
audbackend/core/backend/base.py
audbackend/core/backend/filesystem.py
audbackend/core/backend/minio.py
audbackend/core/interface/__init__.py
audbackend/core/interface/base.py
audbackend/core/interface/maven.py
audbackend/core/interface/unversioned.py
audbackend/core/interface/versioned.py
audbackend/interface/__init__.py
audbackend-2.2.3.dist-info/licenses/LICENSE
docs/changelog.rst
docs/conf.py
docs/conftest.py
docs/contributing.rst
docs/developer-guide.rst
docs/genindex.rst
docs/index.rst
docs/install.rst
docs/legacy.rst
docs/usage.rst
docs/api-src/audbackend.backend.rst
docs/api-src/audbackend.interface.rst
docs/api-src/audbackend.rst
tests/bad_file_system.py
tests/conftest.py
tests/singlefolder.py
tests/test_backend_artifactory.py
tests/test_backend_base.py
tests/test_backend_filesystem.py
tests/test_backend_filesystem_only.py
tests/test_backend_minio.py
tests/test_interface_maven.py
tests/test_interface_unversioned.py
tests/test_interface_versioned.py
tests/test_legacy_import.py
tests/test_repository.py
tests/misc/cleanup_artifactory.py
audbackend-2.2.3.dist-info/METADATA
audbackend-2.2.3.dist-info/WHEEL
audbackend-2.2.3.dist-info/top_level.txt
audbackend-2.2.3.dist-info/RECORD
