Metadata-Version: 2.4
Name: audbackend
Version: 2.2.3
Summary: Backends to access Artifactory and local file system
Author: Johannes Wagner
Author-email: Hagen Wierstorf <hwierstorf@audeering.com>, Christian Geng <cgeng@audeering.com>
License-Expression: MIT
Project-URL: repository, https://github.com/audeering/audbackend/
Project-URL: documentation, https://audeering.github.io/audbackend/
Keywords: artifactory,filesystem,minio,s3
Classifier: Development Status :: 5 - Production/Stable
Classifier: Intended Audience :: Science/Research
Classifier: Intended Audience :: Developers
Classifier: Operating System :: OS Independent
Classifier: Programming Language :: Python
Classifier: Programming Language :: Python :: 3
Classifier: Programming Language :: Python :: 3.10
Classifier: Programming Language :: Python :: 3.11
Classifier: Programming Language :: Python :: 3.12
Classifier: Programming Language :: Python :: 3.13
Classifier: Programming Language :: Python :: 3.14
Classifier: Topic :: Scientific/Engineering
Requires-Python: >=3.10
License-File: LICENSE
Requires-Dist: audeer>=1.20.0
Requires-Dist: pywin32; sys_platform == "win32"
Provides-Extra: artifactory
Requires-Dist: dohq-artifactory>=1.0.1; python_version < "3.14" and extra == "artifactory"
Provides-Extra: minio
Requires-Dist: minio!=7.2.19; extra == "minio"
Provides-Extra: all
Requires-Dist: dohq-artifactory>=1.0.1; python_version < "3.14" and extra == "all"
Requires-Dist: minio; extra == "all"
Dynamic: license-file
